streamlit_rsa_auth_ui/__init__.py
streamlit_rsa_auth_ui/configs.py
streamlit_rsa_auth_ui/encryption.py
streamlit_rsa_auth_ui/events.py
streamlit_rsa_auth_ui/form.py
streamlit_rsa_auth_ui/frontend/build/asset-manifest.json
streamlit_rsa_auth_ui/frontend/build/index.css
streamlit_rsa_auth_ui/frontend/build/index.html
streamlit_rsa_auth_ui/frontend/build/static/js/main.3bc257bc.js
streamlit_rsa_auth_ui/frontend/build/static/js/main.3bc257bc.js.LICENSE.txt
streamlit_rsa_auth_ui/frontend/build/static/js/main.3bc257bc.js.map
streamlit_rsa_auth_ui-1.1.1.dist-info/LICENSE
streamlit_rsa_auth_ui-1.1.1.dist-info/METADATA
streamlit_rsa_auth_ui-1.1.1.dist-info/WHEEL
streamlit_rsa_auth_ui-1.1.1.dist-info/top_level.txt
streamlit_rsa_auth_ui-1.1.1.dist-info/RECORD
