Metadata-Version: 2.1
Name: streamlit-rsa-auth-ui
Version: 1.1.1
Summary: Streamlit RSA Authenticator UI
Home-page: https://github.com/NathanChen198/streamlit-rsa-auth-ui
Author: Nathan Chen
Author-email: nathan.chen.198@gmail.com
Classifier: Programming Language :: Python :: 3.8
Classifier: License :: OSI Approved :: MIT License
Classifier: Operating System :: OS Independent
Requires-Python: >=3.8
License-File: LICENSE
Requires-Dist: streamlit >=1.32
Requires-Dist: rsa >=4.5
Provides-Extra: devel
Requires-Dist: wheel ; extra == 'devel'
Requires-Dist: pytest ==7.4.0 ; extra == 'devel'
Requires-Dist: playwright ==1.39.0 ; extra == 'devel'
Requires-Dist: requests ==2.31.0 ; extra == 'devel'
Requires-Dist: pytest-playwright-snapshot ==1.0 ; extra == 'devel'
Requires-Dist: pytest-rerunfailures ==12.0 ; extra == 'devel'
